shm_reader/__init__.py
shm_reader/cli.py
shm_reader/core.py
shm_reader-0.1.0.dist-info/licenses/LICENSE
shm_reader-0.1.0.dist-info/METADATA
shm_reader-0.1.0.dist-info/WHEEL
shm_reader-0.1.0.dist-info/entry_points.txt
shm_reader-0.1.0.dist-info/top_level.txt
shm_reader-0.1.0.dist-info/RECORD
